pwnedpwd/__init__.py
pwnedpwd/__main__.py
pwnedpwd-0.1.0.dist-info/METADATA
pwnedpwd-0.1.0.dist-info/WHEEL
pwnedpwd-0.1.0.dist-info/LICENSE
pwnedpwd-0.1.0.dist-info/RECORD
